selfcalframework/__init__.py
selfcalframework/imager.py
selfcalframework/selfcal.py
selfcalframework/selfcal_utils.py
selfcalframework-0.1.3.dist-info/LICENSE
selfcalframework-0.1.3.dist-info/METADATA
selfcalframework-0.1.3.dist-info/WHEEL
selfcalframework-0.1.3.dist-info/top_level.txt
selfcalframework-0.1.3.dist-info/RECORD
